dai/__init__.py
dai/definitions.py
dai/factory.py
dai/server.py
dai/worker.py
dai/ITP/__init__.py
dai/ITP/itp.py
WDai-0.2.1.dist-info/METADATA
WDai-0.2.1.dist-info/WHEEL
WDai-0.2.1.dist-info/top_level.txt
WDai-0.2.1.dist-info/RECORD
